{"BaseModel.859da7ca-2d9e-4294-961d-0c931b20c9f4": {"id": "859da7ca-2d9e-4294-961d-0c931b20c9f4", "created_at": "2022-09-02T13:13:08.705876", "updated_at": "2022-09-02T13:13:08.705899", "name": "My_First_Model", "my_number": 89, "__class__": "BaseModel"}, "BaseModel.ad9be289-4980-463e-a36e-eb8e794879fa": {"id": "ad9be289-4980-463e-a36e-eb8e794879fa", "created_at": "2022-09-02T13:23:31.548644", "updated_at": "2022-09-02T13:23:31.548665", "name": "My_First_Model", "my_number": 89, "__class__": "BaseModel"}}